brickse/__init__.py
brickse/api_lego.py
brickse/api_users.py
brickse/brickse.py
brickse/config.py
brickse/objects.py
brickse/request.py
brickse-0.2.0.dist-info/LICENSE
brickse-0.2.0.dist-info/METADATA
brickse-0.2.0.dist-info/WHEEL
brickse-0.2.0.dist-info/top_level.txt
brickse-0.2.0.dist-info/RECORD
