Metadata-Version: 2.1
Name: brickse
Version: 0.2.0
Summary: Python access to BrickSet API.
Home-page: https://github.com/xxao/brickse
Author: Martin Strohalm
Author-email: 
License: MIT
Classifier: Development Status :: 3 - Alpha
Classifier: Programming Language :: Python :: 3 :: Only
Classifier: Operating System :: OS Independent
Classifier: Topic :: Utilities
Classifier: Intended Audience :: Other Audience
License-File: LICENSE
